Workbook

Sheet 🏠 COVER
C3: [ BucketsAI Logo ]
C9: BucketsAI
C11: Reseller Commission Calculator
C14: This tool helps BucketsAI resellers model and compare commission earnings across all four commission modalities (A, B, C, D) for any combination of plans sold. Use the blue input cells in each tab to enter your clients and see your projected commissions instantly.
C21: HOW TO USE
C23: 1. Go to any Modality tab (A, B, C, or D)
C24: 2. Enter your clients in the blue input cells (plan type, billing type, quantity)
C25: 3. View your month-by-month commission schedule and totals
C26: 4. Go to the SCENARIO COMPARISON tab to compare all modalities side by side
C39: =CONCATENATE("Confidential — For Reseller Use Only | BucketsAI | ",TEXT(TODAY(),"MMMM D, YYYY")) -> Confidential — For Reseller Use Only | BucketsAI | February 27, 2026

Sheet 📋 PRICING REFERENCE
B1: BucketsAI — Pricing & Commission Reference
B2: All prices in USD. Use this sheet as your reference guide.
B4: SECTION 1 — Plan Pricing
B5: Plan | C5: Monthly Billing | D5: Annual (per month) | E5: Annual (total) | F5: Monthly vs Annual Savings
B6: Team | C6: 199 | D6: 169 | E6: 2028 | F6: =(C6-D6)/C6 -> 0.15075377
B7: Department | C7: 699 | D7: 589 | E7: 7068 | F7: =(C7-D7)/C7 -> 0.15736767
B8: Company | C8: 1599 | D8: 1349 | E8: 16188 | F8: =(C8-D8)/C8 -> 0.15634772
B11: SECTION 2 — Commission Modality Quick Reference
B12: Modality | C12: Name | D12: Rate | E12: Duration | F12: Billing Type | G12: Best For
B13: A | C13: First Invoice | D13: 1 | E13: Month 1 | F13: Any | G13: Quick cash, fast wins
B14: B | C14: 50% — 3 Months | D14: 50%/mo | E14: Months 1–3 | F14: Any | G14: Short sales cycles
B15: C | C15: 30% — 6 Months | D15: 30%/mo | E15: Months 1–6 | F15: Any | G15: Mid-term clients
B16: D1 | C16: 10% Recurring | D16: 10%/mo | E16: 12 months | F16: Monthly | G16: Stable monthly income
B17: D2 | C17: 12% Committed | D17: 12%/mo | E17: 12 months | F17: Monthly+Commit | G17: Best monthly recurring
B18: D3 | C18: 15% Annual Lump Sum | D18: 15% flat | E18: Month 1 | F18: Annual | G18: Best for annual deals
B21: SECTION 3 — Max Commission per Client — Department Plan
B22: Modality | C22: Max Commission ($)
B23: A | C23: 699
B24: B | C24: 1048.5
B25: C | C25: 1257.3
B26: D1 | C26: 838.8
B27: D2 | C27: 1006.56
B28: D3 | C28: 1060.2

Sheet 💰 MODALITY A
B1: Modality A — First Invoice Commission (100%)
B2: You earn 100% of the first invoice. One payment per client. No recurring.
B5: HOW IT WORKS:
B6: • Monthly plan client: Commission = first monthly invoice amount (one-time)
B7: • Annual plan client: Commission = annual total ÷ 12 (one monthly equivalent, one-time)
B8: • Payment timing: Received once the first invoice is confirmed as paid
B9: • No recurring commissions after Month 1
B11: STEP 1 — Enter your clients below (blue cells are yours to edit)
A12: # | B12: Client Name | C12: Plan | D12: Billing Type | E12: Monthly Rate ($) | F12: Annual Total ($) | G12: Commission Basis ($) | H12: Commission Earned ($) | I12: Payment Period | J12: Notes
A13: 1 | B13: Example | C13: Team | D13: Monthly | E13: 199 | F13: - | G13: 199 | H13: 199 | I13: Month 1 | J13: Example only
A14: 2 | B14: Example | C14: Department | D14: Annual | E14: 589 | F14: 7068 | G14: 589 | H14: 589 | I14: Month 1 | J14: Example only
A15: 3 | B15: Example | C15: Company | D15: Annual | E15: 1349 | F15: 16188 | G15: 1349 | H15: 1349 | I15: Month 1 | J15: Example only
A16: =IF(B16<>"",ROW()-15,"") | E16: =IF(B16="","",IF(C16="Team",IF(D16="Monthly",'📋 PRICING REFERENCE'!C6,'📋 PRICING REFERENCE'!D6),IF(C16="Department",IF(D16="Monthly",'📋 PRICING REFERENCE'!C7,'📋 PRICING REFERENCE'!D7),IF(C16="Company",IF(D16="Monthly",'📋 PRICING REFERENCE'!C8,'📋 PRICING REFERENCE'!D8),"")))) | F16: =IF(B16="","",IF(D16="Annual",IF(C16="Team",'📋 PRICING REFERENCE'!E6,IF(C16="Department",'📋 PRICING REFERENCE'!E7,IF(C16="Company",'📋 PRICING REFERENCE'!E8,""))),"-")) | G16: =IF(B16="","",IF(D16="Monthly",E16,IF(D16="Annual",IF(ISNUMBER(F16),F16/12,""),""))) | H16: =IF(B16="","",G16*1) | I16: =IF(B16="","","Month 1")
A17: =IF(B17<>"",ROW()-15,"") | E17: =IF(B17="","",IF(C17="Team",IF(D17="Monthly",'📋 PRICING REFERENCE'!C7,'📋 PRICING REFERENCE'!D7),IF(C17="Department",IF(D17="Monthly",'📋 PRICING REFERENCE'!C8,'📋 PRICING REFERENCE'!D8),IF(C17="Company",IF(D17="Monthly",'📋 PRICING REFERENCE'!C9,'📋 PRICING REFERENCE'!D9),"")))) | F17: =IF(B17="","",IF(D17="Annual",IF(C17="Team",'📋 PRICING REFERENCE'!E7,IF(C17="Department",'📋 PRICING REFERENCE'!E8,IF(C17="Company",'📋 PRICING REFERENCE'!E9,""))),"-")) | G17: =IF(B17="","",IF(D17="Monthly",E17,IF(D17="Annual",IF(ISNUMBER(F17),F17/12,""),""))) | H17: =IF(B17="","",G17*1) | I17: =IF(B17="","","Month 1")
A18: =IF(B18<>"",ROW()-15,"") | E18: =IF(B18="","",IF(C18="Team",IF(D18="Monthly",'📋 PRICING REFERENCE'!C8,'📋 PRICING REFERENCE'!D8),IF(C18="Department",IF(D18="Monthly",'📋 PRICING REFERENCE'!C9,'📋 PRICING REFERENCE'!D9),IF(C18="Company",IF(D18="Monthly",'📋 PRICING REFERENCE'!C10,'📋 PRICING REFERENCE'!D10),"")))) | F18: =IF(B18="","",IF(D18="Annual",IF(C18="Team",'📋 PRICING REFERENCE'!E8,IF(C18="Department",'📋 PRICING REFERENCE'!E9,IF(C18="Company",'📋 PRICING REFERENCE'!E10,""))),"-")) | G18: =IF(B18="","",IF(D18="Monthly",E18,IF(D18="Annual",IF(ISNUMBER(F18),F18/12,""),""))) | H18: =IF(B18="","",G18*1) | I18: =IF(B18="","","Month 1")
A19: =IF(B19<>"",ROW()-15,"") | E19: =IF(B19="","",IF(C19="Team",IF(D19="Monthly",'📋 PRICING REFERENCE'!C9,'📋 PRICING REFERENCE'!D9),IF(C19="Department",IF(D19="Monthly",'📋 PRICING REFERENCE'!C10,'📋 PRICING REFERENCE'!D10),IF(C19="Company",IF(D19="Monthly",'📋 PRICING REFERENCE'!C11,'📋 PRICING REFERENCE'!D11),"")))) | F19: =IF(B19="","",IF(D19="Annual",IF(C19="Team",'📋 PRICING REFERENCE'!E9,IF(C19="Department",'📋 PRICING REFERENCE'!E10,IF(C19="Company",'📋 PRICING REFERENCE'!E11,""))),"-")) | G19: =IF(B19="","",IF(D19="Monthly",E19,IF(D19="Annual",IF(ISNUMBER(F19),F19/12,""),""))) | H19: =IF(B19="","",G19*1) | I19: =IF(B19="","","Month 1")
A20: =IF(B20<>"",ROW()-15,"") | E20: =IF(B20="","",IF(C20="Team",IF(D20="Monthly",'📋 PRICING REFERENCE'!C10,'📋 PRICING REFERENCE'!D10),IF(C20="Department",IF(D20="Monthly",'📋 PRICING REFERENCE'!C11,'📋 PRICING REFERENCE'!D11),IF(C20="Company",IF(D20="Monthly",'📋 PRICING REFERENCE'!C12,'📋 PRICING REFERENCE'!D12),"")))) | F20: =IF(B20="","",IF(D20="Annual",IF(C20="Team",'📋 PRICING REFERENCE'!E10,IF(C20="Department",'📋 PRICING REFERENCE'!E11,IF(C20="Company",'📋 PRICING REFERENCE'!E12,""))),"-")) | G20: =IF(B20="","",IF(D20="Monthly",E20,IF(D20="Annual",IF(ISNUMBER(F20),F20/12,""),""))) | H20: =IF(B20="","",G20*1) | I20: =IF(B20="","","Month 1")
A21: =IF(B21<>"",ROW()-15,"") | E21: =IF(B21="","",IF(C21="Team",IF(D21="Monthly",'📋 PRICING REFERENCE'!C11,'📋 PRICING REFERENCE'!D11),IF(C21="Department",IF(D21="Monthly",'📋 PRICING REFERENCE'!C12,'📋 PRICING REFERENCE'!D12),IF(C21="Company",IF(D21="Monthly",'📋 PRICING REFERENCE'!C13,'📋 PRICING REFERENCE'!D13),"")))) | F21: =IF(B21="","",IF(D21="Annual",IF(C21="Team",'📋 PRICING REFERENCE'!E11,IF(C21="Department",'📋 PRICING REFERENCE'!E12,IF(C21="Company",'📋 PRICING REFERENCE'!E13,""))),"-")) | G21: =IF(B21="","",IF(D21="Monthly",E21,IF(D21="Annual",IF(ISNUMBER(F21),F21/12,""),""))) | H21: =IF(B21="","",G21*1) | I21: =IF(B21="","","Month 1")
A22: =IF(B22<>"",ROW()-15,"") | E22: =IF(B22="","",IF(C22="Team",IF(D22="Monthly",'📋 PRICING REFERENCE'!C12,'📋 PRICING REFERENCE'!D12),IF(C22="Department",IF(D22="Monthly",'📋 PRICING REFERENCE'!C13,'📋 PRICING REFERENCE'!D13),IF(C22="Company",IF(D22="Monthly",'📋 PRICING REFERENCE'!C14,'📋 PRICING REFERENCE'!D14),"")))) | F22: =IF(B22="","",IF(D22="Annual",IF(C22="Team",'📋 PRICING REFERENCE'!E12,IF(C22="Department",'📋 PRICING REFERENCE'!E13,IF(C22="Company",'📋 PRICING REFERENCE'!E14,""))),"-")) | G22: =IF(B22="","",IF(D22="Monthly",E22,IF(D22="Annual",IF(ISNUMBER(F22),F22/12,""),""))) | H22: =IF(B22="","",G22*1) | I22: =IF(B22="","","Month 1")
A23: =IF(B23<>"",ROW()-15,"") | E23: =IF(B23="","",IF(C23="Team",IF(D23="Monthly",'📋 PRICING REFERENCE'!C13,'📋 PRICING REFERENCE'!D13),IF(C23="Department",IF(D23="Monthly",'📋 PRICING REFERENCE'!C14,'📋 PRICING REFERENCE'!D14),IF(C23="Company",IF(D23="Monthly",'📋 PRICING REFERENCE'!C15,'📋 PRICING REFERENCE'!D15),"")))) | F23: =IF(B23="","",IF(D23="Annual",IF(C23="Team",'📋 PRICING REFERENCE'!E13,IF(C23="Department",'📋 PRICING REFERENCE'!E14,IF(C23="Company",'📋 PRICING REFERENCE'!E15,""))),"-")) | G23: =IF(B23="","",IF(D23="Monthly",E23,IF(D23="Annual",IF(ISNUMBER(F23),F23/12,""),""))) | H23: =IF(B23="","",G23*1) | I23: =IF(B23="","","Month 1")
A24: =IF(B24<>"",ROW()-15,"") | E24: =IF(B24="","",IF(C24="Team",IF(D24="Monthly",'📋 PRICING REFERENCE'!C14,'📋 PRICING REFERENCE'!D14),IF(C24="Department",IF(D24="Monthly",'📋 PRICING REFERENCE'!C15,'📋 PRICING REFERENCE'!D15),IF(C24="Company",IF(D24="Monthly",'📋 PRICING REFERENCE'!C16,'📋 PRICING REFERENCE'!D16),"")))) | F24: =IF(B24="","",IF(D24="Annual",IF(C24="Team",'📋 PRICING REFERENCE'!E14,IF(C24="Department",'📋 PRICING REFERENCE'!E15,IF(C24="Company",'📋 PRICING REFERENCE'!E16,""))),"-")) | G24: =IF(B24="","",IF(D24="Monthly",E24,IF(D24="Annual",IF(ISNUMBER(F24),F24/12,""),""))) | H24: =IF(B24="","",G24*1) | I24: =IF(B24="","","Month 1")
A25: =IF(B25<>"",ROW()-15,"") | E25: =IF(B25="","",IF(C25="Team",IF(D25="Monthly",'📋 PRICING REFERENCE'!C15,'📋 PRICING REFERENCE'!D15),IF(C25="Department",IF(D25="Monthly",'📋 PRICING REFERENCE'!C16,'📋 PRICING REFERENCE'!D16),IF(C25="Company",IF(D25="Monthly",'📋 PRICING REFERENCE'!C17,'📋 PRICING REFERENCE'!D17),"")))) | F25: =IF(B25="","",IF(D25="Annual",IF(C25="Team",'📋 PRICING REFERENCE'!E15,IF(C25="Department",'📋 PRICING REFERENCE'!E16,IF(C25="Company",'📋 PRICING REFERENCE'!E17,""))),"-")) | G25: =IF(B25="","",IF(D25="Monthly",E25,IF(D25="Annual",IF(ISNUMBER(F25),F25/12,""),""))) | H25: =IF(B25="","",G25*1) | I25: =IF(B25="","","Month 1")
A26: =IF(B26<>"",ROW()-15,"") | E26: =IF(B26="","",IF(C26="Team",IF(D26="Monthly",'📋 PRICING REFERENCE'!C16,'📋 PRICING REFERENCE'!D16),IF(C26="Department",IF(D26="Monthly",'📋 PRICING REFERENCE'!C17,'📋 PRICING REFERENCE'!D17),IF(C26="Company",IF(D26="Monthly",'📋 PRICING REFERENCE'!C18,'📋 PRICING REFERENCE'!D18),"")))) | F26: =IF(B26="","",IF(D26="Annual",IF(C26="Team",'📋 PRICING REFERENCE'!E16,IF(C26="Department",'📋 PRICING REFERENCE'!E17,IF(C26="Company",'📋 PRICING REFERENCE'!E18,""))),"-")) | G26: =IF(B26="","",IF(D26="Monthly",E26,IF(D26="Annual",IF(ISNUMBER(F26),F26/12,""),""))) | H26: =IF(B26="","",G26*1) | I26: =IF(B26="","","Month 1")
A27: =IF(B27<>"",ROW()-15,"") | E27: =IF(B27="","",IF(C27="Team",IF(D27="Monthly",'📋 PRICING REFERENCE'!C17,'📋 PRICING REFERENCE'!D17),IF(C27="Department",IF(D27="Monthly",'📋 PRICING REFERENCE'!C18,'📋 PRICING REFERENCE'!D18),IF(C27="Company",IF(D27="Monthly",'📋 PRICING REFERENCE'!C19,'📋 PRICING REFERENCE'!D19),"")))) | F27: =IF(B27="","",IF(D27="Annual",IF(C27="Team",'📋 PRICING REFERENCE'!E17,IF(C27="Department",'📋 PRICING REFERENCE'!E18,IF(C27="Company",'📋 PRICING REFERENCE'!E19,""))),"-")) | G27: =IF(B27="","",IF(D27="Monthly",E27,IF(D27="Annual",IF(ISNUMBER(F27),F27/12,""),""))) | H27: =IF(B27="","",G27*1) | I27: =IF(B27="","","Month 1")
... A35: =IF(B35<>"",ROW()-15,"") | E35: =IF(B35="","",IF(C35="Team",IF(D35="Monthly",'📋 PRICING REFERENCE'!C25,'📋 PRICING REFERENCE'!D25),IF(C35="Department",IF(D35="Monthly",'📋 PRICING REFERENCE'!C26,'📋 PRICING REFERENCE'!D26),IF(C35="Company",IF(D35="Monthly",'📋 PRICING REFERENCE'!C27,'📋 PRICING REFERENCE'!D27),"")))) | F35: =IF(B35="","",IF(D35="Annual",IF(C35="Team",'📋 PRICING REFERENCE'!E25,IF(C35="Department",'📋 PRICING REFERENCE'!E26,IF(C35="Company",'📋 PRICING REFERENCE'!E27,""))),"-")) | G35: =IF(B35="","",IF(D35="Monthly",E35,IF(D35="Annual",IF(ISNUMBER(F35),F35/12,""),""))) | H35: =IF(B35="","",G35*1) | I35: =IF(B35="","","Month 1")
B37: SUMMARY
B38: Total Clients Entered | G38: =COUNTA(B16:B35) -> 0
B39: Total Commission — Month 1 | G39: =SUM(H16:H35) -> 0
B40: Average Commission per Client | G40: =IFERROR(SUM(H16:H35)/COUNTA(B16:B35),0) -> 0
B41: Largest Single Commission | G41: =IFERROR(MAX(H16:H35),0) -> 0
B43: MONTHLY PAYOUT SCHEDULE
B44: Mo 1 | C44: Mo 2 | D44: Mo 3 | E44: Mo 4 | F44: Mo 5 | G44: Mo 6 | H44: Mo 7 | I44: Mo 8 | J44: Mo 9 | K44: Mo 10 | L44: Mo 11 | M44: Mo 12 | N44: TOTAL
A45: All Clients | B45: =SUM(H16:H35) -> 0 | C45: 0 | D45: 0 | E45: 0 | F45: 0 | G45: 0 | H45: 0 | I45: 0 | J45: 0 | K45: 0 | L45: 0 | M45: 0 | N45: =SUM(B45:M45) -> 0

Sheet 💰 MODALITY B
B1: Modality B — 50% Commission for 3 Months
B2: You earn 50% of each invoice for the first 3 months only.
B5: HOW IT WORKS:
B6: • Monthly plan: 50% × monthly invoice × months 1, 2, 3
B7: • Annual plan: 50% × (annual total ÷ 12) × months 1, 2, 3
B8: • No commission from Month 4 onward
B9: • Payment: each month as the client's invoice is confirmed paid
B11: STEP 1 — Enter your clients below (blue cells are yours to edit)
A12: # | B12: Client Name | C12: Plan | D12: Billing Type | E12: Monthly Rate ($) | F12: Annual Total ($) | G12: Commission Basis ($) | H12: Commission per Month ($) | I12: Payment Period | J12: Notes | K12: Total Commission (3 mo)
A13: 1 | B13: Example | C13: Department | D13: Monthly | E13: 699 | F13: - | G13: 699 | H13: 349.5 | I13: Months 1–3 | J13: Example only | K13: 1048.5
A14: 2 | B14: Example | C14: Company | D14: Annual | E14: 1349 | F14: 16188 | G14: 1349 | H14: 674.5 | I14: Months 1–3 | J14: Example only | K14: 2023.5
A15: 3 | B15: Example | C15: Team | D15: Monthly | E15: 199 | F15: - | G15: 199 | H15: 99.5 | I15: Months 1–3 | J15: Example only | K15: 298.5
A16: =IF(B16<>"",ROW()-15,"") | E16: =IF(B16="","",IF(C16="Team",IF(D16="Monthly",'📋 PRICING REFERENCE'!C6,'📋 PRICING REFERENCE'!D6),IF(C16="Department",IF(D16="Monthly",'📋 PRICING REFERENCE'!C7,'📋 PRICING REFERENCE'!D7),IF(C16="Company",IF(D16="Monthly",'📋 PRICING REFERENCE'!C8,'📋 PRICING REFERENCE'!D8),"")))) | F16: =IF(B16="","",IF(D16="Annual",IF(C16="Team",'📋 PRICING REFERENCE'!E6,IF(C16="Department",'📋 PRICING REFERENCE'!E7,IF(C16="Company",'📋 PRICING REFERENCE'!E8,""))),"-")) | G16: =IF(B16="","",IF(D16="Monthly",E16,IF(D16="Annual",IF(ISNUMBER(F16),F16/12,""),""))) | H16: =IF(B16="","",G16*0.5) | I16: =IF(B16="","","Months 1–3") | K16: =IF(B16="","",H16*3)
A17: =IF(B17<>"",ROW()-15,"") | E17: =IF(B17="","",IF(C17="Team",IF(D17="Monthly",'📋 PRICING REFERENCE'!C7,'📋 PRICING REFERENCE'!D7),IF(C17="Department",IF(D17="Monthly",'📋 PRICING REFERENCE'!C8,'📋 PRICING REFERENCE'!D8),IF(C17="Company",IF(D17="Monthly",'📋 PRICING REFERENCE'!C9,'📋 PRICING REFERENCE'!D9),"")))) | F17: =IF(B17="","",IF(D17="Annual",IF(C17="Team",'📋 PRICING REFERENCE'!E7,IF(C17="Department",'📋 PRICING REFERENCE'!E8,IF(C17="Company",'📋 PRICING REFERENCE'!E9,""))),"-")) | G17: =IF(B17="","",IF(D17="Monthly",E17,IF(D17="Annual",IF(ISNUMBER(F17),F17/12,""),""))) | H17: =IF(B17="","",G17*0.5) | I17: =IF(B17="","","Months 1–3") | K17: =IF(B17="","",H17*3)
A18: =IF(B18<>"",ROW()-15,"") | E18: =IF(B18="","",IF(C18="Team",IF(D18="Monthly",'📋 PRICING REFERENCE'!C8,'📋 PRICING REFERENCE'!D8),IF(C18="Department",IF(D18="Monthly",'📋 PRICING REFERENCE'!C9,'📋 PRICING REFERENCE'!D9),IF(C18="Company",IF(D18="Monthly",'📋 PRICING REFERENCE'!C10,'📋 PRICING REFERENCE'!D10),"")))) | F18: =IF(B18="","",IF(D18="Annual",IF(C18="Team",'📋 PRICING REFERENCE'!E8,IF(C18="Department",'📋 PRICING REFERENCE'!E9,IF(C18="Company",'📋 PRICING REFERENCE'!E10,""))),"-")) | G18: =IF(B18="","",IF(D18="Monthly",E18,IF(D18="Annual",IF(ISNUMBER(F18),F18/12,""),""))) | H18: =IF(B18="","",G18*0.5) | I18: =IF(B18="","","Months 1–3") | K18: =IF(B18="","",H18*3)
A19: =IF(B19<>"",ROW()-15,"") | E19: =IF(B19="","",IF(C19="Team",IF(D19="Monthly",'📋 PRICING REFERENCE'!C9,'📋 PRICING REFERENCE'!D9),IF(C19="Department",IF(D19="Monthly",'📋 PRICING REFERENCE'!C10,'📋 PRICING REFERENCE'!D10),IF(C19="Company",IF(D19="Monthly",'📋 PRICING REFERENCE'!C11,'📋 PRICING REFERENCE'!D11),"")))) | F19: =IF(B19="","",IF(D19="Annual",IF(C19="Team",'📋 PRICING REFERENCE'!E9,IF(C19="Department",'📋 PRICING REFERENCE'!E10,IF(C19="Company",'📋 PRICING REFERENCE'!E11,""))),"-")) | G19: =IF(B19="","",IF(D19="Monthly",E19,IF(D19="Annual",IF(ISNUMBER(F19),F19/12,""),""))) | H19: =IF(B19="","",G19*0.5) | I19: =IF(B19="","","Months 1–3") | K19: =IF(B19="","",H19*3)
A20: =IF(B20<>"",ROW()-15,"") | E20: =IF(B20="","",IF(C20="Team",IF(D20="Monthly",'📋 PRICING REFERENCE'!C10,'📋 PRICING REFERENCE'!D10),IF(C20="Department",IF(D20="Monthly",'📋 PRICING REFERENCE'!C11,'📋 PRICING REFERENCE'!D11),IF(C20="Company",IF(D20="Monthly",'📋 PRICING REFERENCE'!C12,'📋 PRICING REFERENCE'!D12),"")))) | F20: =IF(B20="","",IF(D20="Annual",IF(C20="Team",'📋 PRICING REFERENCE'!E10,IF(C20="Department",'📋 PRICING REFERENCE'!E11,IF(C20="Company",'📋 PRICING REFERENCE'!E12,""))),"-")) | G20: =IF(B20="","",IF(D20="Monthly",E20,IF(D20="Annual",IF(ISNUMBER(F20),F20/12,""),""))) | H20: =IF(B20="","",G20*0.5) | I20: =IF(B20="","","Months 1–3") | K20: =IF(B20="","",H20*3)
A21: =IF(B21<>"",ROW()-15,"") | E21: =IF(B21="","",IF(C21="Team",IF(D21="Monthly",'📋 PRICING REFERENCE'!C11,'📋 PRICING REFERENCE'!D11),IF(C21="Department",IF(D21="Monthly",'📋 PRICING REFERENCE'!C12,'📋 PRICING REFERENCE'!D12),IF(C21="Company",IF(D21="Monthly",'📋 PRICING REFERENCE'!C13,'📋 PRICING REFERENCE'!D13),"")))) | F21: =IF(B21="","",IF(D21="Annual",IF(C21="Team",'📋 PRICING REFERENCE'!E11,IF(C21="Department",'📋 PRICING REFERENCE'!E12,IF(C21="Company",'📋 PRICING REFERENCE'!E13,""))),"-")) | G21: =IF(B21="","",IF(D21="Monthly",E21,IF(D21="Annual",IF(ISNUMBER(F21),F21/12,""),""))) | H21: =IF(B21="","",G21*0.5) | I21: =IF(B21="","","Months 1–3") | K21: =IF(B21="","",H21*3)
A22: =IF(B22<>"",ROW()-15,"") | E22: =IF(B22="","",IF(C22="Team",IF(D22="Monthly",'📋 PRICING REFERENCE'!C12,'📋 PRICING REFERENCE'!D12),IF(C22="Department",IF(D22="Monthly",'📋 PRICING REFERENCE'!C13,'📋 PRICING REFERENCE'!D13),IF(C22="Company",IF(D22="Monthly",'📋 PRICING REFERENCE'!C14,'📋 PRICING REFERENCE'!D14),"")))) | F22: =IF(B22="","",IF(D22="Annual",IF(C22="Team",'📋 PRICING REFERENCE'!E12,IF(C22="Department",'📋 PRICING REFERENCE'!E13,IF(C22="Company",'📋 PRICING REFERENCE'!E14,""))),"-")) | G22: =IF(B22="","",IF(D22="Monthly",E22,IF(D22="Annual",IF(ISNUMBER(F22),F22/12,""),""))) | H22: =IF(B22="","",G22*0.5) | I22: =IF(B22="","","Months 1–3") | K22: =IF(B22="","",H22*3)
A23: =IF(B23<>"",ROW()-15,"") | E23: =IF(B23="","",IF(C23="Team",IF(D23="Monthly",'📋 PRICING REFERENCE'!C13,'📋 PRICING REFERENCE'!D13),IF(C23="Department",IF(D23="Monthly",'📋 PRICING REFERENCE'!C14,'📋 PRICING REFERENCE'!D14),IF(C23="Company",IF(D23="Monthly",'📋 PRICING REFERENCE'!C15,'📋 PRICING REFERENCE'!D15),"")))) | F23: =IF(B23="","",IF(D23="Annual",IF(C23="Team",'📋 PRICING REFERENCE'!E13,IF(C23="Department",'📋 PRICING REFERENCE'!E14,IF(C23="Company",'📋 PRICING REFERENCE'!E15,""))),"-")) | G23: =IF(B23="","",IF(D23="Monthly",E23,IF(D23="Annual",IF(ISNUMBER(F23),F23/12,""),""))) | H23: =IF(B23="","",G23*0.5) | I23: =IF(B23="","","Months 1–3") | K23: =IF(B23="","",H23*3)
A24: =IF(B24<>"",ROW()-15,"") | E24: =IF(B24="","",IF(C24="Team",IF(D24="Monthly",'📋 PRICING REFERENCE'!C14,'📋 PRICING REFERENCE'!D14),IF(C24="Department",IF(D24="Monthly",'📋 PRICING REFERENCE'!C15,'📋 PRICING REFERENCE'!D15),IF(C24="Company",IF(D24="Monthly",'📋 PRICING REFERENCE'!C16,'📋 PRICING REFERENCE'!D16),"")))) | F24: =IF(B24="","",IF(D24="Annual",IF(C24="Team",'📋 PRICING REFERENCE'!E14,IF(C24="Department",'📋 PRICING REFERENCE'!E15,IF(C24="Company",'📋 PRICING REFERENCE'!E16,""))),"-")) | G24: =IF(B24="","",IF(D24="Monthly",E24,IF(D24="Annual",IF(ISNUMBER(F24),F24/12,""),""))) | H24: =IF(B24="","",G24*0.5) | I24: =IF(B24="","","Months 1–3") | K24: =IF(B24="","",H24*3)
A25: =IF(B25<>"",ROW()-15,"") | E25: =IF(B25="","",IF(C25="Team",IF(D25="Monthly",'📋 PRICING REFERENCE'!C15,'📋 PRICING REFERENCE'!D15),IF(C25="Department",IF(D25="Monthly",'📋 PRICING REFERENCE'!C16,'📋 PRICING REFERENCE'!D16),IF(C25="Company",IF(D25="Monthly",'📋 PRICING REFERENCE'!C17,'📋 PRICING REFERENCE'!D17),"")))) | F25: =IF(B25="","",IF(D25="Annual",IF(C25="Team",'📋 PRICING REFERENCE'!E15,IF(C25="Department",'📋 PRICING REFERENCE'!E16,IF(C25="Company",'📋 PRICING REFERENCE'!E17,""))),"-")) | G25: =IF(B25="","",IF(D25="Monthly",E25,IF(D25="Annual",IF(ISNUMBER(F25),F25/12,""),""))) | H25: =IF(B25="","",G25*0.5) | I25: =IF(B25="","","Months 1–3") | K25: =IF(B25="","",H25*3)
A26: =IF(B26<>"",ROW()-15,"") | E26: =IF(B26="","",IF(C26="Team",IF(D26="Monthly",'📋 PRICING REFERENCE'!C16,'📋 PRICING REFERENCE'!D16),IF(C26="Department",IF(D26="Monthly",'📋 PRICING REFERENCE'!C17,'📋 PRICING REFERENCE'!D17),IF(C26="Company",IF(D26="Monthly",'📋 PRICING REFERENCE'!C18,'📋 PRICING REFERENCE'!D18),"")))) | F26: =IF(B26="","",IF(D26="Annual",IF(C26="Team",'📋 PRICING REFERENCE'!E16,IF(C26="Department",'📋 PRICING REFERENCE'!E17,IF(C26="Company",'📋 PRICING REFERENCE'!E18,""))),"-")) | G26: =IF(B26="","",IF(D26="Monthly",E26,IF(D26="Annual",IF(ISNUMBER(F26),F26/12,""),""))) | H26: =IF(B26="","",G26*0.5) | I26: =IF(B26="","","Months 1–3") | K26: =IF(B26="","",H26*3)
A27: =IF(B27<>"",ROW()-15,"") | E27: =IF(B27="","",IF(C27="Team",IF(D27="Monthly",'📋 PRICING REFERENCE'!C17,'📋 PRICING REFERENCE'!D17),IF(C27="Department",IF(D27="Monthly",'📋 PRICING REFERENCE'!C18,'📋 PRICING REFERENCE'!D18),IF(C27="Company",IF(D27="Monthly",'📋 PRICING REFERENCE'!C19,'📋 PRICING REFERENCE'!D19),"")))) | F27: =IF(B27="","",IF(D27="Annual",IF(C27="Team",'📋 PRICING REFERENCE'!E17,IF(C27="Department",'📋 PRICING REFERENCE'!E18,IF(C27="Company",'📋 PRICING REFERENCE'!E19,""))),"-")) | G27: =IF(B27="","",IF(D27="Monthly",E27,IF(D27="Annual",IF(ISNUMBER(F27),F27/12,""),""))) | H27: =IF(B27="","",G27*0.5) | I27: =IF(B27="","","Months 1–3") | K27: =IF(B27="","",H27*3)
... A35: =IF(B35<>"",ROW()-15,"") | E35: =IF(B35="","",IF(C35="Team",IF(D35="Monthly",'📋 PRICING REFERENCE'!C25,'📋 PRICING REFERENCE'!D25),IF(C35="Department",IF(D35="Monthly",'📋 PRICING REFERENCE'!C26,'📋 PRICING REFERENCE'!D26),IF(C35="Company",IF(D35="Monthly",'📋 PRICING REFERENCE'!C27,'📋 PRICING REFERENCE'!D27),"")))) | F35: =IF(B35="","",IF(D35="Annual",IF(C35="Team",'📋 PRICING REFERENCE'!E25,IF(C35="Department",'📋 PRICING REFERENCE'!E26,IF(C35="Company",'📋 PRICING REFERENCE'!E27,""))),"-")) | G35: =IF(B35="","",IF(D35="Monthly",E35,IF(D35="Annual",IF(ISNUMBER(F35),F35/12,""),""))) | H35: =IF(B35="","",G35*0.5) | I35: =IF(B35="","","Months 1–3") | K35: =IF(B35="","",H35*3)
B37: SUMMARY
B38: Total Clients Entered | G38: =COUNTA(B16:B35) -> 0
B39: Total Commission per Month | G39: =SUM(H16:H35) -> 0
B40: Total Commission over 3 Months | G40: =SUM(K16:K35) -> 0
B41: Average Commission per Client (3 mo) | G41: =IFERROR(SUM(K16:K35)/COUNTA(B16:B35),0) -> 0
B42: Largest Single Client Total | G42: =IFERROR(MAX(K16:K35),0) -> 0
A44: MONTHLY PAYOUT SCHEDULE
B45: Mo 1 | C45: Mo 2 | D45: Mo 3 | E45: Mo 4 | F45: Mo 5 | G45: Mo 6 | H45: Mo 7 | I45: Mo 8 | J45: Mo 9 | K45: Mo 10 | L45: Mo 11 | M45: Mo 12 | N45: TOTAL
A46: All Clients | B46: =IF(1<=3,SUM(H16:H35),0) -> 0 | C46: =IF(2<=3,SUM(H16:H35),0) -> 0 | D46: =IF(3<=3,SUM(H16:H35),0) -> 0 | E46: =IF(4<=3,SUM(H16:H35),0) -> 0 | F46: =IF(5<=3,SUM(H16:H35),0) -> 0 | G46: =IF(6<=3,SUM(H16:H35),0) -> 0 | H46: =IF(7<=3,SUM(H16:H35),0) -> 0 | I46: =IF(8<=3,SUM(H16:H35),0) -> 0 | J46: =IF(9<=3,SUM(H16:H35),0) -> 0 | K46: =IF(10<=3,SUM(H16:H35),0) -> 0 | L46: =IF(11<=3,SUM(H16:H35),0) -> 0 | M46: =IF(12<=3,SUM(H16:H35),0) -> 0 | N46: =SUM(B46:M46) -> 0

Sheet 💰 MODALITY C
B1: Modality C — 30% Commission for 6 Months
B2: You earn 30% of each invoice for the first 6 months only.
B5: HOW IT WORKS:
B6: • Monthly plan: 30% × monthly invoice × months 1 through 6
B7: • Annual plan: 30% × (annual total ÷ 12) × months 1 through 6
B8: • No commission from Month 7 onward
B9: • Payment: each month as the client's invoice is confirmed paid
B11: STEP 1 — Enter your clients below (blue cells are yours to edit)
A12: # | B12: Client Name | C12: Plan | D12: Billing Type | E12: Monthly Rate ($) | F12: Annual Total ($) | G12: Commission Basis ($) | H12: Commission per Month ($) | I12: Payment Period | J12: Notes | K12: Total Commission (6 mo)
A13: 1 | B13: Example | C13: Team | D13: Monthly | E13: 199 | F13: - | G13: 199 | H13: 59.7 | I13: Months 1-6 | J13: Example only | K13: 358.2
A14: 2 | B14: Example | C14: Department | D14: Annual | E14: 589 | F14: 7068 | G14: 589 | H14: 176.7 | I14: Months 1-6 | J14: Example only | K14: 1060.2
A15: 3 | B15: Example | C15: Company | D15: Monthly | E15: 1599 | F15: - | G15: 1599 | H15: 479.7 | I15: Months 1-6 | J15: Example only | K15: 2878.2
A16: =IF(B16<>"",ROW()-15,"") | E16: =IF(B16="","",IF(C16="Team",IF(D16="Monthly",'📋 PRICING REFERENCE'!C6,'📋 PRICING REFERENCE'!D6),IF(C16="Department",IF(D16="Monthly",'📋 PRICING REFERENCE'!C7,'📋 PRICING REFERENCE'!D7),IF(C16="Company",IF(D16="Monthly",'📋 PRICING REFERENCE'!C8,'📋 PRICING REFERENCE'!D8),"")))) | F16: =IF(B16="","",IF(D16="Annual",IF(C16="Team",'📋 PRICING REFERENCE'!E6,IF(C16="Department",'📋 PRICING REFERENCE'!E7,IF(C16="Company",'📋 PRICING REFERENCE'!E8,""))),"-")) | G16: =IF(B16="","",IF(D16="Monthly",E16,IF(D16="Annual",IF(ISNUMBER(F16),F16/12,""),""))) | H16: =IF(B16="","",G16*0.3) | I16: =IF(B16="","","Months 1-6") | K16: =IF(B16="","",H16*6)
A17: =IF(B17<>"",ROW()-15,"") | E17: =IF(B17="","",IF(C17="Team",IF(D17="Monthly",'📋 PRICING REFERENCE'!C7,'📋 PRICING REFERENCE'!D7),IF(C17="Department",IF(D17="Monthly",'📋 PRICING REFERENCE'!C8,'📋 PRICING REFERENCE'!D8),IF(C17="Company",IF(D17="Monthly",'📋 PRICING REFERENCE'!C9,'📋 PRICING REFERENCE'!D9),"")))) | F17: =IF(B17="","",IF(D17="Annual",IF(C17="Team",'📋 PRICING REFERENCE'!E7,IF(C17="Department",'📋 PRICING REFERENCE'!E8,IF(C17="Company",'📋 PRICING REFERENCE'!E9,""))),"-")) | G17: =IF(B17="","",IF(D17="Monthly",E17,IF(D17="Annual",IF(ISNUMBER(F17),F17/12,""),""))) | H17: =IF(B17="","",G17*0.3) | I17: =IF(B17="","","Months 1-6") | K17: =IF(B17="","",H17*6)
A18: =IF(B18<>"",ROW()-15,"") | E18: =IF(B18="","",IF(C18="Team",IF(D18="Monthly",'📋 PRICING REFERENCE'!C8,'📋 PRICING REFERENCE'!D8),IF(C18="Department",IF(D18="Monthly",'📋 PRICING REFERENCE'!C9,'📋 PRICING REFERENCE'!D9),IF(C18="Company",IF(D18="Monthly",'📋 PRICING REFERENCE'!C10,'📋 PRICING REFERENCE'!D10),"")))) | F18: =IF(B18="","",IF(D18="Annual",IF(C18="Team",'📋 PRICING REFERENCE'!E8,IF(C18="Department",'📋 PRICING REFERENCE'!E9,IF(C18="Company",'📋 PRICING REFERENCE'!E10,""))),"-")) | G18: =IF(B18="","",IF(D18="Monthly",E18,IF(D18="Annual",IF(ISNUMBER(F18),F18/12,""),""))) | H18: =IF(B18="","",G18*0.3) | I18: =IF(B18="","","Months 1-6") | K18: =IF(B18="","",H18*6)
A19: =IF(B19<>"",ROW()-15,"") | E19: =IF(B19="","",IF(C19="Team",IF(D19="Monthly",'📋 PRICING REFERENCE'!C9,'📋 PRICING REFERENCE'!D9),IF(C19="Department",IF(D19="Monthly",'📋 PRICING REFERENCE'!C10,'📋 PRICING REFERENCE'!D10),IF(C19="Company",IF(D19="Monthly",'📋 PRICING REFERENCE'!C11,'📋 PRICING REFERENCE'!D11),"")))) | F19: =IF(B19="","",IF(D19="Annual",IF(C19="Team",'📋 PRICING REFERENCE'!E9,IF(C19="Department",'📋 PRICING REFERENCE'!E10,IF(C19="Company",'📋 PRICING REFERENCE'!E11,""))),"-")) | G19: =IF(B19="","",IF(D19="Monthly",E19,IF(D19="Annual",IF(ISNUMBER(F19),F19/12,""),""))) | H19: =IF(B19="","",G19*0.3) | I19: =IF(B19="","","Months 1-6") | K19: =IF(B19="","",H19*6)
A20: =IF(B20<>"",ROW()-15,"") | E20: =IF(B20="","",IF(C20="Team",IF(D20="Monthly",'📋 PRICING REFERENCE'!C10,'📋 PRICING REFERENCE'!D10),IF(C20="Department",IF(D20="Monthly",'📋 PRICING REFERENCE'!C11,'📋 PRICING REFERENCE'!D11),IF(C20="Company",IF(D20="Monthly",'📋 PRICING REFERENCE'!C12,'📋 PRICING REFERENCE'!D12),"")))) | F20: =IF(B20="","",IF(D20="Annual",IF(C20="Team",'📋 PRICING REFERENCE'!E10,IF(C20="Department",'📋 PRICING REFERENCE'!E11,IF(C20="Company",'📋 PRICING REFERENCE'!E12,""))),"-")) | G20: =IF(B20="","",IF(D20="Monthly",E20,IF(D20="Annual",IF(ISNUMBER(F20),F20/12,""),""))) | H20: =IF(B20="","",G20*0.3) | I20: =IF(B20="","","Months 1-6") | K20: =IF(B20="","",H20*6)
A21: =IF(B21<>"",ROW()-15,"") | E21: =IF(B21="","",IF(C21="Team",IF(D21="Monthly",'📋 PRICING REFERENCE'!C11,'📋 PRICING REFERENCE'!D11),IF(C21="Department",IF(D21="Monthly",'📋 PRICING REFERENCE'!C12,'📋 PRICING REFERENCE'!D12),IF(C21="Company",IF(D21="Monthly",'📋 PRICING REFERENCE'!C13,'📋 PRICING REFERENCE'!D13),"")))) | F21: =IF(B21="","",IF(D21="Annual",IF(C21="Team",'📋 PRICING REFERENCE'!E11,IF(C21="Department",'📋 PRICING REFERENCE'!E12,IF(C21="Company",'📋 PRICING REFERENCE'!E13,""))),"-")) | G21: =IF(B21="","",IF(D21="Monthly",E21,IF(D21="Annual",IF(ISNUMBER(F21),F21/12,""),""))) | H21: =IF(B21="","",G21*0.3) | I21: =IF(B21="","","Months 1-6") | K21: =IF(B21="","",H21*6)
A22: =IF(B22<>"",ROW()-15,"") | E22: =IF(B22="","",IF(C22="Team",IF(D22="Monthly",'📋 PRICING REFERENCE'!C12,'📋 PRICING REFERENCE'!D12),IF(C22="Department",IF(D22="Monthly",'📋 PRICING REFERENCE'!C13,'📋 PRICING REFERENCE'!D13),IF(C22="Company",IF(D22="Monthly",'📋 PRICING REFERENCE'!C14,'📋 PRICING REFERENCE'!D14),"")))) | F22: =IF(B22="","",IF(D22="Annual",IF(C22="Team",'📋 PRICING REFERENCE'!E12,IF(C22="Department",'📋 PRICING REFERENCE'!E13,IF(C22="Company",'📋 PRICING REFERENCE'!E14,""))),"-")) | G22: =IF(B22="","",IF(D22="Monthly",E22,IF(D22="Annual",IF(ISNUMBER(F22),F22/12,""),""))) | H22: =IF(B22="","",G22*0.3) | I22: =IF(B22="","","Months 1-6") | K22: =IF(B22="","",H22*6)
A23: =IF(B23<>"",ROW()-15,"") | E23: =IF(B23="","",IF(C23="Team",IF(D23="Monthly",'📋 PRICING REFERENCE'!C13,'📋 PRICING REFERENCE'!D13),IF(C23="Department",IF(D23="Monthly",'📋 PRICING REFERENCE'!C14,'📋 PRICING REFERENCE'!D14),IF(C23="Company",IF(D23="Monthly",'📋 PRICING REFERENCE'!C15,'📋 PRICING REFERENCE'!D15),"")))) | F23: =IF(B23="","",IF(D23="Annual",IF(C23="Team",'📋 PRICING REFERENCE'!E13,IF(C23="Department",'📋 PRICING REFERENCE'!E14,IF(C23="Company",'📋 PRICING REFERENCE'!E15,""))),"-")) | G23: =IF(B23="","",IF(D23="Monthly",E23,IF(D23="Annual",IF(ISNUMBER(F23),F23/12,""),""))) | H23: =IF(B23="","",G23*0.3) | I23: =IF(B23="","","Months 1-6") | K23: =IF(B23="","",H23*6)
A24: =IF(B24<>"",ROW()-15,"") | E24: =IF(B24="","",IF(C24="Team",IF(D24="Monthly",'📋 PRICING REFERENCE'!C14,'📋 PRICING REFERENCE'!D14),IF(C24="Department",IF(D24="Monthly",'📋 PRICING REFERENCE'!C15,'📋 PRICING REFERENCE'!D15),IF(C24="Company",IF(D24="Monthly",'📋 PRICING REFERENCE'!C16,'📋 PRICING REFERENCE'!D16),"")))) | F24: =IF(B24="","",IF(D24="Annual",IF(C24="Team",'📋 PRICING REFERENCE'!E14,IF(C24="Department",'📋 PRICING REFERENCE'!E15,IF(C24="Company",'📋 PRICING REFERENCE'!E16,""))),"-")) | G24: =IF(B24="","",IF(D24="Monthly",E24,IF(D24="Annual",IF(ISNUMBER(F24),F24/12,""),""))) | H24: =IF(B24="","",G24*0.3) | I24: =IF(B24="","","Months 1-6") | K24: =IF(B24="","",H24*6)
A25: =IF(B25<>"",ROW()-15,"") | E25: =IF(B25="","",IF(C25="Team",IF(D25="Monthly",'📋 PRICING REFERENCE'!C15,'📋 PRICING REFERENCE'!D15),IF(C25="Department",IF(D25="Monthly",'📋 PRICING REFERENCE'!C16,'📋 PRICING REFERENCE'!D16),IF(C25="Company",IF(D25="Monthly",'📋 PRICING REFERENCE'!C17,'📋 PRICING REFERENCE'!D17),"")))) | F25: =IF(B25="","",IF(D25="Annual",IF(C25="Team",'📋 PRICING REFERENCE'!E15,IF(C25="Department",'📋 PRICING REFERENCE'!E16,IF(C25="Company",'📋 PRICING REFERENCE'!E17,""))),"-")) | G25: =IF(B25="","",IF(D25="Monthly",E25,IF(D25="Annual",IF(ISNUMBER(F25),F25/12,""),""))) | H25: =IF(B25="","",G25*0.3) | I25: =IF(B25="","","Months 1-6") | K25: =IF(B25="","",H25*6)
A26: =IF(B26<>"",ROW()-15,"") | E26: =IF(B26="","",IF(C26="Team",IF(D26="Monthly",'📋 PRICING REFERENCE'!C16,'📋 PRICING REFERENCE'!D16),IF(C26="Department",IF(D26="Monthly",'📋 PRICING REFERENCE'!C17,'📋 PRICING REFERENCE'!D17),IF(C26="Company",IF(D26="Monthly",'📋 PRICING REFERENCE'!C18,'📋 PRICING REFERENCE'!D18),"")))) | F26: =IF(B26="","",IF(D26="Annual",IF(C26="Team",'📋 PRICING REFERENCE'!E16,IF(C26="Department",'📋 PRICING REFERENCE'!E17,IF(C26="Company",'📋 PRICING REFERENCE'!E18,""))),"-")) | G26: =IF(B26="","",IF(D26="Monthly",E26,IF(D26="Annual",IF(ISNUMBER(F26),F26/12,""),""))) | H26: =IF(B26="","",G26*0.3) | I26: =IF(B26="","","Months 1-6") | K26: =IF(B26="","",H26*6)
A27: =IF(B27<>"",ROW()-15,"") | E27: =IF(B27="","",IF(C27="Team",IF(D27="Monthly",'📋 PRICING REFERENCE'!C17,'📋 PRICING REFERENCE'!D17),IF(C27="Department",IF(D27="Monthly",'📋 PRICING REFERENCE'!C18,'📋 PRICING REFERENCE'!D18),IF(C27="Company",IF(D27="Monthly",'📋 PRICING REFERENCE'!C19,'📋 PRICING REFERENCE'!D19),"")))) | F27: =IF(B27="","",IF(D27="Annual",IF(C27="Team",'📋 PRICING REFERENCE'!E17,IF(C27="Department",'📋 PRICING REFERENCE'!E18,IF(C27="Company",'📋 PRICING REFERENCE'!E19,""))),"-")) | G27: =IF(B27="","",IF(D27="Monthly",E27,IF(D27="Annual",IF(ISNUMBER(F27),F27/12,""),""))) | H27: =IF(B27="","",G27*0.3) | I27: =IF(B27="","","Months 1-6") | K27: =IF(B27="","",H27*6)
... A35: =IF(B35<>"",ROW()-15,"") | E35: =IF(B35="","",IF(C35="Team",IF(D35="Monthly",'📋 PRICING REFERENCE'!C25,'📋 PRICING REFERENCE'!D25),IF(C35="Department",IF(D35="Monthly",'📋 PRICING REFERENCE'!C26,'📋 PRICING REFERENCE'!D26),IF(C35="Company",IF(D35="Monthly",'📋 PRICING REFERENCE'!C27,'📋 PRICING REFERENCE'!D27),"")))) | F35: =IF(B35="","",IF(D35="Annual",IF(C35="Team",'📋 PRICING REFERENCE'!E25,IF(C35="Department",'📋 PRICING REFERENCE'!E26,IF(C35="Company",'📋 PRICING REFERENCE'!E27,""))),"-")) | G35: =IF(B35="","",IF(D35="Monthly",E35,IF(D35="Annual",IF(ISNUMBER(F35),F35/12,""),""))) | H35: =IF(B35="","",G35*0.3) | I35: =IF(B35="","","Months 1-6") | K35: =IF(B35="","",H35*6)
B37: SUMMARY
B38: Total Clients Entered | G38: =COUNTA(B16:B35) -> 0
B39: Total Commission per Month | G39: =SUM(H16:H35) -> 0
B40: Total Commission over 6 Months | G40: =SUM(K16:K35) -> 0
B41: Average Commission per Client (6 mo) | G41: =IFERROR(SUM(K16:K35)/COUNTA(B16:B35),0) -> 0
B42: Largest Single Client Total | G42: =IFERROR(MAX(K16:K35),0) -> 0
A44: MONTHLY PAYOUT SCHEDULE
B45: Mo 1 | C45: Mo 2 | D45: Mo 3 | E45: Mo 4 | F45: Mo 5 | G45: Mo 6 | H45: Mo 7 | I45: Mo 8 | J45: Mo 9 | K45: Mo 10 | L45: Mo 11 | M45: Mo 12 | N45: TOTAL
A46: All Clients | B46: =IF(1<=6,SUM(H16:H35),0) -> 0 | C46: =IF(2<=6,SUM(H16:H35),0) -> 0 | D46: =IF(3<=6,SUM(H16:H35),0) -> 0 | E46: =IF(4<=6,SUM(H16:H35),0) -> 0 | F46: =IF(5<=6,SUM(H16:H35),0) -> 0 | G46: =IF(6<=6,SUM(H16:H35),0) -> 0 | H46: =IF(7<=6,SUM(H16:H35),0) -> 0 | I46: =IF(8<=6,SUM(H16:H35),0) -> 0 | J46: =IF(9<=6,SUM(H16:H35),0) -> 0 | K46: =IF(10<=6,SUM(H16:H35),0) -> 0 | L46: =IF(11<=6,SUM(H16:H35),0) -> 0 | M46: =IF(12<=6,SUM(H16:H35),0) -> 0 | N46: =SUM(B46:M46) -> 0

Sheet 💰 MODALITY D
B5: HOW IT WORKS — THREE SUB-TYPES:
B6: D1 — Monthly plan, no annual commitment:
B7: 10% of each monthly invoice, paid for 12 consecutive months
B8: D2 — Monthly plan WITH 12-month signed contract:
B9: 12% of each monthly invoice, paid for 12 consecutive months
B10: (Requires a formal 12-month commitment from the client)
B11: D3 — Annual plan (any tier):
B12: 15% of the TOTAL annual plan value, paid as a single lump sum
B14: STEP 1 — Enter your clients below (blue cells are yours to edit)
A15: # | B15: Client Name | C15: Plan | D15: Sub-type | E15: Monthly Rate ($) | F15: Annual Total ($) | G15: Commission Rate (%) | H15: Commission ($) | I15: Duration | J15: Total Commission ($) | K15: Notes
A16: 1 | B16: Example | C16: Department | D16: D1 | E16: 699 | F16: - | G16: 0.1 | H16: 69.9 | I16: 12 months | J16: 838.8 | K16: No commitment
A17: 2 | B17: Example | C17: Company | D17: D2 | E17: 1599 | F17: - | G17: 0.12 | H17: 191.88 | I17: 12 months | J17: 2302.56 | K17: 12-mo contract
A18: 3 | B18: Example | C18: Team | D18: D3 | E18: 169 | F18: 2028 | G18: 0.15 | H18: 304.2 | I18: Month 1 (lump sum) | J18: 304.2 | K18: Annual plan
A19: 4 | B19: Example | C19: Company | D19: D3 | E19: 1349 | F19: 16188 | G19: 0.15 | H19: 2428.2 | I19: Month 1 (lump sum) | J19: 2428.2 | K19: Annual plan
A20: =IF(B20<>"",ROW()-19,"") | E20: =IF(B20="","",IF(D20="D3",IF(C20="Team",'📋 PRICING REFERENCE'!D6,IF(C20="Department",'📋 PRICING REFERENCE'!D7,IF(C20="Company",'📋 PRICING REFERENCE'!D8,""))),IF(C20="Team",'📋 PRICING REFERENCE'!C6,IF(C20="Department",'📋 PRICING REFERENCE'!C7,IF(C20="Company",'📋 PRICING REFERENCE'!C8,""))))) | F20: =IF(B20="","",IF(D20="D3",IF(C20="Team",'📋 PRICING REFERENCE'!E6,IF(C20="Department",'📋 PRICING REFERENCE'!E7,IF(C20="Company",'📋 PRICING REFERENCE'!E8,""))),"-")) | G20: =IF(B20="","",IF(D20="D1",0.1,IF(D20="D2",0.12,IF(D20="D3",0.15,"")))) | H20: =IF(B20="","",IF(OR(D20="D1",D20="D2"),E20*G20,IF(D20="D3",F20*G20,""))) | I20: =IF(B20="","",IF(OR(D20="D1",D20="D2"),"12 months",IF(D20="D3","Month 1 (lump sum)",""))) | J20: =IF(B20="","",IF(OR(D20="D1",D20="D2"),H20*12,IF(D20="D3",H20,"")))
A21: =IF(B21<>"",ROW()-19,"") | E21: =IF(B21="","",IF(D21="D3",IF(C21="Team",'📋 PRICING REFERENCE'!D7,IF(C21="Department",'📋 PRICING REFERENCE'!D8,IF(C21="Company",'📋 PRICING REFERENCE'!D9,""))),IF(C21="Team",'📋 PRICING REFERENCE'!C7,IF(C21="Department",'📋 PRICING REFERENCE'!C8,IF(C21="Company",'📋 PRICING REFERENCE'!C9,""))))) | F21: =IF(B21="","",IF(D21="D3",IF(C21="Team",'📋 PRICING REFERENCE'!E7,IF(C21="Department",'📋 PRICING REFERENCE'!E8,IF(C21="Company",'📋 PRICING REFERENCE'!E9,""))),"-")) | G21: =IF(B21="","",IF(D21="D1",0.1,IF(D21="D2",0.12,IF(D21="D3",0.15,"")))) | H21: =IF(B21="","",IF(OR(D21="D1",D21="D2"),E21*G21,IF(D21="D3",F21*G21,""))) | I21: =IF(B21="","",IF(OR(D21="D1",D21="D2"),"12 months",IF(D21="D3","Month 1 (lump sum)",""))) | J21: =IF(B21="","",IF(OR(D21="D1",D21="D2"),H21*12,IF(D21="D3",H21,"")))
A22: =IF(B22<>"",ROW()-19,"") | E22: =IF(B22="","",IF(D22="D3",IF(C22="Team",'📋 PRICING REFERENCE'!D8,IF(C22="Department",'📋 PRICING REFERENCE'!D9,IF(C22="Company",'📋 PRICING REFERENCE'!D10,""))),IF(C22="Team",'📋 PRICING REFERENCE'!C8,IF(C22="Department",'📋 PRICING REFERENCE'!C9,IF(C22="Company",'📋 PRICING REFERENCE'!C10,""))))) | F22: =IF(B22="","",IF(D22="D3",IF(C22="Team",'📋 PRICING REFERENCE'!E8,IF(C22="Department",'📋 PRICING REFERENCE'!E9,IF(C22="Company",'📋 PRICING REFERENCE'!E10,""))),"-")) | G22: =IF(B22="","",IF(D22="D1",0.1,IF(D22="D2",0.12,IF(D22="D3",0.15,"")))) | H22: =IF(B22="","",IF(OR(D22="D1",D22="D2"),E22*G22,IF(D22="D3",F22*G22,""))) | I22: =IF(B22="","",IF(OR(D22="D1",D22="D2"),"12 months",IF(D22="D3","Month 1 (lump sum)",""))) | J22: =IF(B22="","",IF(OR(D22="D1",D22="D2"),H22*12,IF(D22="D3",H22,"")))
A23: =IF(B23<>"",ROW()-19,"") | E23: =IF(B23="","",IF(D23="D3",IF(C23="Team",'📋 PRICING REFERENCE'!D9,IF(C23="Department",'📋 PRICING REFERENCE'!D10,IF(C23="Company",'📋 PRICING REFERENCE'!D11,""))),IF(C23="Team",'📋 PRICING REFERENCE'!C9,IF(C23="Department",'📋 PRICING REFERENCE'!C10,IF(C23="Company",'📋 PRICING REFERENCE'!C11,""))))) | F23: =IF(B23="","",IF(D23="D3",IF(C23="Team",'📋 PRICING REFERENCE'!E9,IF(C23="Department",'📋 PRICING REFERENCE'!E10,IF(C23="Company",'📋 PRICING REFERENCE'!E11,""))),"-")) | G23: =IF(B23="","",IF(D23="D1",0.1,IF(D23="D2",0.12,IF(D23="D3",0.15,"")))) | H23: =IF(B23="","",IF(OR(D23="D1",D23="D2"),E23*G23,IF(D23="D3",F23*G23,""))) | I23: =IF(B23="","",IF(OR(D23="D1",D23="D2"),"12 months",IF(D23="D3","Month 1 (lump sum)",""))) | J23: =IF(B23="","",IF(OR(D23="D1",D23="D2"),H23*12,IF(D23="D3",H23,"")))
A24: =IF(B24<>"",ROW()-19,"") | E24: =IF(B24="","",IF(D24="D3",IF(C24="Team",'📋 PRICING REFERENCE'!D10,IF(C24="Department",'📋 PRICING REFERENCE'!D11,IF(C24="Company",'📋 PRICING REFERENCE'!D12,""))),IF(C24="Team",'📋 PRICING REFERENCE'!C10,IF(C24="Department",'📋 PRICING REFERENCE'!C11,IF(C24="Company",'📋 PRICING REFERENCE'!C12,""))))) | F24: =IF(B24="","",IF(D24="D3",IF(C24="Team",'📋 PRICING REFERENCE'!E10,IF(C24="Department",'📋 PRICING REFERENCE'!E11,IF(C24="Company",'📋 PRICING REFERENCE'!E12,""))),"-")) | G24: =IF(B24="","",IF(D24="D1",0.1,IF(D24="D2",0.12,IF(D24="D3",0.15,"")))) | H24: =IF(B24="","",IF(OR(D24="D1",D24="D2"),E24*G24,IF(D24="D3",F24*G24,""))) | I24: =IF(B24="","",IF(OR(D24="D1",D24="D2"),"12 months",IF(D24="D3","Month 1 (lump sum)",""))) | J24: =IF(B24="","",IF(OR(D24="D1",D24="D2"),H24*12,IF(D24="D3",H24,"")))
A25: =IF(B25<>"",ROW()-19,"") | E25: =IF(B25="","",IF(D25="D3",IF(C25="Team",'📋 PRICING REFERENCE'!D11,IF(C25="Department",'📋 PRICING REFERENCE'!D12,IF(C25="Company",'📋 PRICING REFERENCE'!D13,""))),IF(C25="Team",'📋 PRICING REFERENCE'!C11,IF(C25="Department",'📋 PRICING REFERENCE'!C12,IF(C25="Company",'📋 PRICING REFERENCE'!C13,""))))) | F25: =IF(B25="","",IF(D25="D3",IF(C25="Team",'📋 PRICING REFERENCE'!E11,IF(C25="Department",'📋 PRICING REFERENCE'!E12,IF(C25="Company",'📋 PRICING REFERENCE'!E13,""))),"-")) | G25: =IF(B25="","",IF(D25="D1",0.1,IF(D25="D2",0.12,IF(D25="D3",0.15,"")))) | H25: =IF(B25="","",IF(OR(D25="D1",D25="D2"),E25*G25,IF(D25="D3",F25*G25,""))) | I25: =IF(B25="","",IF(OR(D25="D1",D25="D2"),"12 months",IF(D25="D3","Month 1 (lump sum)",""))) | J25: =IF(B25="","",IF(OR(D25="D1",D25="D2"),H25*12,IF(D25="D3",H25,"")))
A26: =IF(B26<>"",ROW()-19,"") | E26: =IF(B26="","",IF(D26="D3",IF(C26="Team",'📋 PRICING REFERENCE'!D12,IF(C26="Department",'📋 PRICING REFERENCE'!D13,IF(C26="Company",'📋 PRICING REFERENCE'!D14,""))),IF(C26="Team",'📋 PRICING REFERENCE'!C12,IF(C26="Department",'📋 PRICING REFERENCE'!C13,IF(C26="Company",'📋 PRICING REFERENCE'!C14,""))))) | F26: =IF(B26="","",IF(D26="D3",IF(C26="Team",'📋 PRICING REFERENCE'!E12,IF(C26="Department",'📋 PRICING REFERENCE'!E13,IF(C26="Company",'📋 PRICING REFERENCE'!E14,""))),"-")) | G26: =IF(B26="","",IF(D26="D1",0.1,IF(D26="D2",0.12,IF(D26="D3",0.15,"")))) | H26: =IF(B26="","",IF(OR(D26="D1",D26="D2"),E26*G26,IF(D26="D3",F26*G26,""))) | I26: =IF(B26="","",IF(OR(D26="D1",D26="D2"),"12 months",IF(D26="D3","Month 1 (lump sum)",""))) | J26: =IF(B26="","",IF(OR(D26="D1",D26="D2"),H26*12,IF(D26="D3",H26,"")))
A27: =IF(B27<>"",ROW()-19,"") | E27: =IF(B27="","",IF(D27="D3",IF(C27="Team",'📋 PRICING REFERENCE'!D13,IF(C27="Department",'📋 PRICING REFERENCE'!D14,IF(C27="Company",'📋 PRICING REFERENCE'!D15,""))),IF(C27="Team",'📋 PRICING REFERENCE'!C13,IF(C27="Department",'📋 PRICING REFERENCE'!C14,IF(C27="Company",'📋 PRICING REFERENCE'!C15,""))))) | F27: =IF(B27="","",IF(D27="D3",IF(C27="Team",'📋 PRICING REFERENCE'!E13,IF(C27="Department",'📋 PRICING REFERENCE'!E14,IF(C27="Company",'📋 PRICING REFERENCE'!E15,""))),"-")) | G27: =IF(B27="","",IF(D27="D1",0.1,IF(D27="D2",0.12,IF(D27="D3",0.15,"")))) | H27: =IF(B27="","",IF(OR(D27="D1",D27="D2"),E27*G27,IF(D27="D3",F27*G27,""))) | I27: =IF(B27="","",IF(OR(D27="D1",D27="D2"),"12 months",IF(D27="D3","Month 1 (lump sum)",""))) | J27: =IF(B27="","",IF(OR(D27="D1",D27="D2"),H27*12,IF(D27="D3",H27,"")))
A28: =IF(B28<>"",ROW()-19,"") | E28: =IF(B28="","",IF(D28="D3",IF(C28="Team",'📋 PRICING REFERENCE'!D14,IF(C28="Department",'📋 PRICING REFERENCE'!D15,IF(C28="Company",'📋 PRICING REFERENCE'!D16,""))),IF(C28="Team",'📋 PRICING REFERENCE'!C14,IF(C28="Department",'📋 PRICING REFERENCE'!C15,IF(C28="Company",'📋 PRICING REFERENCE'!C16,""))))) | F28: =IF(B28="","",IF(D28="D3",IF(C28="Team",'📋 PRICING REFERENCE'!E14,IF(C28="Department",'📋 PRICING REFERENCE'!E15,IF(C28="Company",'📋 PRICING REFERENCE'!E16,""))),"-")) | G28: =IF(B28="","",IF(D28="D1",0.1,IF(D28="D2",0.12,IF(D28="D3",0.15,"")))) | H28: =IF(B28="","",IF(OR(D28="D1",D28="D2"),E28*G28,IF(D28="D3",F28*G28,""))) | I28: =IF(B28="","",IF(OR(D28="D1",D28="D2"),"12 months",IF(D28="D3","Month 1 (lump sum)",""))) | J28: =IF(B28="","",IF(OR(D28="D1",D28="D2"),H28*12,IF(D28="D3",H28,"")))
A29: =IF(B29<>"",ROW()-19,"") | E29: =IF(B29="","",IF(D29="D3",IF(C29="Team",'📋 PRICING REFERENCE'!D15,IF(C29="Department",'📋 PRICING REFERENCE'!D16,IF(C29="Company",'📋 PRICING REFERENCE'!D17,""))),IF(C29="Team",'📋 PRICING REFERENCE'!C15,IF(C29="Department",'📋 PRICING REFERENCE'!C16,IF(C29="Company",'📋 PRICING REFERENCE'!C17,""))))) | F29: =IF(B29="","",IF(D29="D3",IF(C29="Team",'📋 PRICING REFERENCE'!E15,IF(C29="Department",'📋 PRICING REFERENCE'!E16,IF(C29="Company",'📋 PRICING REFERENCE'!E17,""))),"-")) | G29: =IF(B29="","",IF(D29="D1",0.1,IF(D29="D2",0.12,IF(D29="D3",0.15,"")))) | H29: =IF(B29="","",IF(OR(D29="D1",D29="D2"),E29*G29,IF(D29="D3",F29*G29,""))) | I29: =IF(B29="","",IF(OR(D29="D1",D29="D2"),"12 months",IF(D29="D3","Month 1 (lump sum)",""))) | J29: =IF(B29="","",IF(OR(D29="D1",D29="D2"),H29*12,IF(D29="D3",H29,"")))
A30: =IF(B30<>"",ROW()-19,"") | E30: =IF(B30="","",IF(D30="D3",IF(C30="Team",'📋 PRICING REFERENCE'!D16,IF(C30="Department",'📋 PRICING REFERENCE'!D17,IF(C30="Company",'📋 PRICING REFERENCE'!D18,""))),IF(C30="Team",'📋 PRICING REFERENCE'!C16,IF(C30="Department",'📋 PRICING REFERENCE'!C17,IF(C30="Company",'📋 PRICING REFERENCE'!C18,""))))) | F30: =IF(B30="","",IF(D30="D3",IF(C30="Team",'📋 PRICING REFERENCE'!E16,IF(C30="Department",'📋 PRICING REFERENCE'!E17,IF(C30="Company",'📋 PRICING REFERENCE'!E18,""))),"-")) | G30: =IF(B30="","",IF(D30="D1",0.1,IF(D30="D2",0.12,IF(D30="D3",0.15,"")))) | H30: =IF(B30="","",IF(OR(D30="D1",D30="D2"),E30*G30,IF(D30="D3",F30*G30,""))) | I30: =IF(B30="","",IF(OR(D30="D1",D30="D2"),"12 months",IF(D30="D3","Month 1 (lump sum)",""))) | J30: =IF(B30="","",IF(OR(D30="D1",D30="D2"),H30*12,IF(D30="D3",H30,"")))
A31: =IF(B31<>"",ROW()-19,"") | E31: =IF(B31="","",IF(D31="D3",IF(C31="Team",'📋 PRICING REFERENCE'!D17,IF(C31="Department",'📋 PRICING REFERENCE'!D18,IF(C31="Company",'📋 PRICING REFERENCE'!D19,""))),IF(C31="Team",'📋 PRICING REFERENCE'!C17,IF(C31="Department",'📋 PRICING REFERENCE'!C18,IF(C31="Company",'📋 PRICING REFERENCE'!C19,""))))) | F31: =IF(B31="","",IF(D31="D3",IF(C31="Team",'📋 PRICING REFERENCE'!E17,IF(C31="Department",'📋 PRICING REFERENCE'!E18,IF(C31="Company",'📋 PRICING REFERENCE'!E19,""))),"-")) | G31: =IF(B31="","",IF(D31="D1",0.1,IF(D31="D2",0.12,IF(D31="D3",0.15,"")))) | H31: =IF(B31="","",IF(OR(D31="D1",D31="D2"),E31*G31,IF(D31="D3",F31*G31,""))) | I31: =IF(B31="","",IF(OR(D31="D1",D31="D2"),"12 months",IF(D31="D3","Month 1 (lump sum)",""))) | J31: =IF(B31="","",IF(OR(D31="D1",D31="D2"),H31*12,IF(D31="D3",H31,"")))
... A39: =IF(B39<>"",ROW()-19,"") | E39: =IF(B39="","",IF(D39="D3",IF(C39="Team",'📋 PRICING REFERENCE'!D25,IF(C39="Department",'📋 PRICING REFERENCE'!D26,IF(C39="Company",'📋 PRICING REFERENCE'!D27,""))),IF(C39="Team",'📋 PRICING REFERENCE'!C25,IF(C39="Department",'📋 PRICING REFERENCE'!C26,IF(C39="Company",'📋 PRICING REFERENCE'!C27,""))))) | F39: =IF(B39="","",IF(D39="D3",IF(C39="Team",'📋 PRICING REFERENCE'!E25,IF(C39="Department",'📋 PRICING REFERENCE'!E26,IF(C39="Company",'📋 PRICING REFERENCE'!E27,""))),"-")) | G39: =IF(B39="","",IF(D39="D1",0.1,IF(D39="D2",0.12,IF(D39="D3",0.15,"")))) | H39: =IF(B39="","",IF(OR(D39="D1",D39="D2"),E39*G39,IF(D39="D3",F39*G39,""))) | I39: =IF(B39="","",IF(OR(D39="D1",D39="D2"),"12 months",IF(D39="D3","Month 1 (lump sum)",""))) | J39: =IF(B39="","",IF(OR(D39="D1",D39="D2"),H39*12,IF(D39="D3",H39,"")))
B41: SUB-TOTALS BY TYPE
B42: Sub-type | C42: Description | D42: Client Count | E42: Monthly Commission | F42: Total Commission
B43: D1 | C43: 10% x 12 months (no commitment) | D43: =COUNTIF(D20:D39,"D1") -> 0 | E43: {=SUMPRODUCT((D20:D39="D1")*IF(ISNUMBER(H20:H39),H20:H39,0))} -> 0 | F43: {=SUMPRODUCT((D20:D39="D1")*IF(ISNUMBER(J20:J39),J20:J39,0))} -> 0
B44: D2 | C44: 12% x 12 months (annual commitment) | D44: =COUNTIF(D20:D39,"D2") -> 0 | E44: {=SUMPRODUCT((D20:D39="D2")*IF(ISNUMBER(H20:H39),H20:H39,0))} -> 0 | F44: {=SUMPRODUCT((D20:D39="D2")*IF(ISNUMBER(J20:J39),J20:J39,0))} -> 0
B45: D3 | C45: 15% annual lump sum | D45: =COUNTIF(D20:D39,"D3") -> 0 | E45: {=SUMPRODUCT((D20:D39="D3")*IF(ISNUMBER(H20:H39),H20:H39,0))} -> 0 | F45: {=SUMPRODUCT((D20:D39="D3")*IF(ISNUMBER(J20:J39),J20:J39,0))} -> 0
B48: GRAND TOTAL (All D Sub-types) | F48: =SUM(F43:F45) -> 0
A50: MONTHLY PAYOUT SCHEDULE
B51: Mo 1 | C51: Mo 2 | D51: Mo 3 | E51: Mo 4 | F51: Mo 5 | G51: Mo 6 | H51: Mo 7 | I51: Mo 8 | J51: Mo 9 | K51: Mo 10 | L51: Mo 11 | M51: Mo 12 | N51: TOTAL
A52: D1 | B52: =E43 -> 0 | C52: =E43 -> 0 | D52: =E43 -> 0 | E52: =E43 -> 0 | F52: =E43 -> 0 | G52: =E43 -> 0 | H52: =E43 -> 0 | I52: =E43 -> 0 | J52: =E43 -> 0 | K52: =E43 -> 0 | L52: =E43 -> 0 | M52: =E43 -> 0 | N52: =SUM(B52:M52) -> 0
A53: D2 | B53: =E44 -> 0 | C53: =E44 -> 0 | D53: =E44 -> 0 | E53: =E44 -> 0 | F53: =E44 -> 0 | G53: =E44 -> 0 | H53: =E44 -> 0 | I53: =E44 -> 0 | J53: =E44 -> 0 | K53: =E44 -> 0 | L53: =E44 -> 0 | M53: =E44 -> 0 | N53: =SUM(B53:M53) -> 0
A54: D3 | B54: =E45 -> 0 | C54: 0 | D54: 0 | E54: 0 | F54: 0 | G54: 0 | H54: 0 | I54: 0 | J54: 0 | K54: 0 | L54: 0 | M54: 0 | N54: =SUM(B54:M54) -> 0
A55: TOTAL | B55: =SUM(B52:B54) -> 0 | C55: =SUM(C52:C54) -> 0 | D55: =SUM(D52:D54) -> 0 | E55: =SUM(E52:E54) -> 0 | F55: =SUM(F52:F54) -> 0 | G55: =SUM(G52:G54) -> 0 | H55: =SUM(H52:H54) -> 0 | I55: =SUM(I52:I54) -> 0 | ... M55: =SUM(M52:M54) -> 0 | N55: =SUM(B55:M55) -> 0

Sheet 📊 SCENARIO COMPARISON
B8: Client Name: | C8: Sample Client
B9: Plan: | C9: Department
B10: Billing Type: | C10: Monthly
B12: Monthly Rate: | C12: =IF(C9="Team",IF(C10="Monthly",'📋 PRICING REFERENCE'!C6,'📋 PRICING REFERENCE'!D6),IF(C9="Department",IF(C10="Monthly",'📋 PRICING REFERENCE'!C7,'📋 PRICING REFERENCE'!D7),IF(C9="Company",IF(C10="Monthly",'📋 PRICING REFERENCE'!C8,'📋 PRICING REFERENCE'!D8),""))) -> 699
B13: Annual Total: | C13: =IF(C10="Annual",IF(C9="Team",'📋 PRICING REFERENCE'!E6,IF(C9="Department",'📋 PRICING REFERENCE'!E7,IF(C9="Company",'📋 PRICING REFERENCE'!E8,""))),"-") -> -
B14: Commission Basis: | C14: =IF(C10="Monthly",C12,IF(C10="Annual",IF(ISNUMBER(C13),C13/12,""),"")) -> 699
B16: Modality | C16: Description | D16: Mo 1 | E16: Mo 2 | F16: Mo 3 | G16: Mo 4-6 (ea) | H16: Mo 7-12 (ea) | I16: TOTAL
B17: A | C17: First Invoice (100%) | D17: =C14*1 -> 699 | E17: 0 | F17: 0 | G17: 0 | H17: 0 | I17: =D17 -> 699
B18: B | C18: 50% x 3 months | D18: =C14*0.5 -> 349.5 | E18: =C14*0.5 -> 349.5 | F18: =C14*0.5 -> 349.5 | G18: 0 | H18: 0 | I18: =C14*0.5*3 -> 1048.5
B19: C | C19: 30% x 6 months | D19: =C14*0.3 -> 209.7 | E19: =C14*0.3 -> 209.7 | F19: =C14*0.3 -> 209.7 | G19: =C14*0.3 -> 209.7 | H19: 0 | I19: =C14*0.3*6 -> 1258.2
B20: D1 | C20: 10% x 12 months | D20: =IF(C10="Monthly",C12*0.1,0) -> 69.9 | E20: =IF(C10="Monthly",C12*0.1,0) -> 69.9 | F20: =IF(C10="Monthly",C12*0.1,0) -> 69.9 | G20: =IF(C10="Monthly",C12*0.1,0) -> 69.9 | H20: =IF(C10="Monthly",C12*0.1,0) -> 69.9 | I20: =IF(C10="Monthly",C12*0.1*12,0) -> 838.8
B21: D2 | C21: 12% x 12 mo (commit) | D21: =IF(C10="Monthly",C12*0.12,0) -> 83.88 | E21: =IF(C10="Monthly",C12*0.12,0) -> 83.88 | F21: =IF(C10="Monthly",C12*0.12,0) -> 83.88 | G21: =IF(C10="Monthly",C12*0.12,0) -> 83.88 | H21: =IF(C10="Monthly",C12*0.12,0) -> 83.88 | I21: =IF(C10="Monthly",C12*0.12*12,0) -> 1006.56
B22: D3 | C22: 15% annual lump sum | D22: =IF(C10="Annual",C13*0.15,0) -> 0 | E22: 0 | F22: 0 | G22: 0 | H22: 0 | I22: =IF(C10="Annual",C13*0.15,0) -> 0
B23: ⭐ BEST Modality: | D23: =IF(I17=MAX(I17:I22),"A",IF(I18=MAX(I17:I22),"B",IF(I19=MAX(I17:I22),"C",IF(I20=MAX(I17:I22),"D1",IF(I21=MAX(I17:I22),"D2","D3"))))) -> C | E23: with total commission of: | G23: =MAX(I17:I22) -> 1258.2
B25: RECOMMENDATION
B26: =CONCATENATE("Based on your selection (",C9," / ",C10,"), your best modality is ",D23," with a total commission of $",TEXT(G23,"#,##0.00"),".") -> Based on your selection (Department / Monthly), your best modality is C with a total commission of $1258,2000.
B27: =IF(OR(D23="D3"),"💡 Consider negotiating an annual contract with your client to maximize your earnings upfront.",IF(OR(D23="D1",D23="D2"),"💡 The recurring structure rewards you for client retention — focus on onboarding this client successfully.",IF(D23="A","💡 Modality A gives you 100% upfront — ideal for quick cash flow.",IF(D23="B","💡 Modality B balances upfront earnings with a short commitment period.","💡 Modality C spreads earnings over 6 months for a balanced approach.")))) -> 💡 Modality C spreads earnings over 6 months for a balanced approach.
B30: FULL PORTFOLIO COMPARISON — Totals from Each Modality Tab
B31: Modality | C31: Tab Source | D31: Total Clients | E31: Total Commission | F31: Avg per Client | G31: Best For
B32: A | C32: Modality A tab | D32: =COUNTA('💰 MODALITY A'!B16:B35) -> 0 | E32: =SUM('💰 MODALITY A'!H16:H35) -> 0 | F32: =IFERROR(E32/D32,0) -> 0 | G32: Quick cash
B33: B | C33: Modality B tab | D33: =COUNTA('💰 MODALITY B'!B16:B35) -> 0 | E33: =SUM('💰 MODALITY B'!K16:K35) -> 0 | F33: =IFERROR(E33/D33,0) -> 0 | G33: 3-month clients
B34: C | C34: Modality C tab | D34: =COUNTA('💰 MODALITY C'!B16:B35) -> 0 | E34: =SUM('💰 MODALITY C'!K16:K35) -> 0 | F34: =IFERROR(E34/D34,0) -> 0 | G34: 6-month clients
B35: D (all) | C35: Modality D tab | D35: =COUNTA('💰 MODALITY D'!B20:B39) -> 0 | E35: =SUM('💰 MODALITY D'!J20:J39) -> 0 | F35: =IFERROR(E35/D35,0) -> 0 | G35: Long-term clients
B36: ⭐ HIGHEST Portfolio Commission: | E36: =MAX(E32:E35) -> 0
B57: Month | C57: 1 | D57: 2 | E57: 3 | F57: 4 | G57: 5 | H57: 6 | I57: 7 | J57: 8 | K57: 9 | L57: 10 | M57: 11 | N57: 12
B58: A | C58: =$C$14 -> 699 | D58: 0 | E58: 0 | F58: 0 | G58: 0 | H58: 0 | I58: 0 | J58: 0 | K58: 0 | L58: 0 | M58: 0 | N58: 0
B59: B | C59: =$C$14*0.5 -> 349.5 | D59: =$C$14*0.5 -> 349.5 | E59: =$C$14*0.5 -> 349.5 | F59: 0 | G59: 0 | H59: 0 | I59: 0 | J59: 0 | K59: 0 | L59: 0 | M59: 0 | N59: 0
B60: C | C60: =$C$14*0.3 -> 209.7 | D60: =$C$14*0.3 -> 209.7 | E60: =$C$14*0.3 -> 209.7 | F60: =$C$14*0.3 -> 209.7 | G60: =$C$14*0.3 -> 209.7 | H60: =$C$14*0.3 -> 209.7 | I60: 0 | J60: 0 | K60: 0 | L60: 0 | M60: 0 | N60: 0
B61: D1 | C61: =IF($C$10="Monthly",$C$12*0.1,0) -> 69.9 | D61: =IF($C$10="Monthly",$C$12*0.1,0) -> 69.9 | E61: =IF($C$10="Monthly",$C$12*0.1,0) -> 69.9 | F61: =IF($C$10="Monthly",$C$12*0.1,0) -> 69.9 | G61: =IF($C$10="Monthly",$C$12*0.1,0) -> 69.9 | H61: =IF($C$10="Monthly",$C$12*0.1,0) -> 69.9 | I61: =IF($C$10="Monthly",$C$12*0.1,0) -> 69.9 | J61: =IF($C$10="Monthly",$C$12*0.1,0) -> 69.9 | ... N61: =IF($C$10="Monthly",$C$12*0.1,0) -> 69.9
B62: D2 | C62: =IF($C$10="Monthly",$C$12*0.12,0) -> 83.88 | D62: =IF($C$10="Monthly",$C$12*0.12,0) -> 83.88 | E62: =IF($C$10="Monthly",$C$12*0.12,0) -> 83.88 | F62: =IF($C$10="Monthly",$C$12*0.12,0) -> 83.88 | G62: =IF($C$10="Monthly",$C$12*0.12,0) -> 83.88 | H62: =IF($C$10="Monthly",$C$12*0.12,0) -> 83.88 | I62: =IF($C$10="Monthly",$C$12*0.12,0) -> 83.88 | J62: =IF($C$10="Monthly",$C$12*0.12,0) -> 83.88 | ... N62: =IF($C$10="Monthly",$C$12*0.12,0) -> 83.88
B63: D3 | C63: =IF($C$10="Annual",$C$13*0.15,0) -> 0 | D63: 0 | E63: 0 | F63: 0 | G63: 0 | H63: 0 | I63: 0 | J63: 0 | K63: 0 | L63: 0 | M63: 0 | N63: 0
B66: KEY INSIGHTS
B67: To maximize TOTAL earnings: | E67: To maximize FAST cash: | H67: To maximize RECURRING income:
B68: D2 (12% x 12 mo) yields the highest total for monthly clients. D3 (15%) is best for annual plans. | E68: Modality A gives 100% of the first invoice immediately. Best for uncertain retention. | H68: D1 and D2 spread commissions over 12 months for predictable recurring income.
